Workbook
Name _BQ4.1: '[1]#REF'!$A$1:$E$370
Name _BQ4.2: '[1]#REF'!$A$1:$F$43
Name _Fill: #REF!
Name _Fill: #REF!
Name _Order1: 255
Name _Ser1: IF([2]Sheet1!#REF!=1,[2]Sheet1!#REF!,[2]Sheet1!#REF!)
Name _Ser1: IF([2]Sheet1!#REF!=1,[2]Sheet1!#REF!,[2]Sheet1!#REF!)
Name _Ser2: IF([2]Sheet1!#REF!=1,[2]Sheet1!#REF!,[2]Sheet1!#REF!)
Name _Ser2: IF([2]Sheet1!#REF!=1,[2]Sheet1!#REF!,[2]Sheet1!#REF!)
Name _Ser3: IF([2]Sheet1!#REF!=1,[2]Sheet1!#REF!,[2]Sheet1!#REF!)
Name _Ser3: IF([2]Sheet1!#REF!=1,[2]Sheet1!#REF!,[2]Sheet1!#REF!)
Name _Ser4: IF([2]Sheet1!#REF!=1,[2]Sheet1!#REF!,[2]Sheet1!#REF!)
Name Account: #REF!
Name Account: #REF!
Name AccountsTM1: #REF!
Name AccountsTM1: #REF!
Name Adj: #REF!
Name Adj: #REF!
Name ADJUSTMENTS: #REF!
Name Affiliate_List: #REF!
Name All_Months: [3]Global!$L$3:$L$26
Name ASB: #REF!
Name ASB: #REF!
Name BLANK: #REF!
Name BLANK: #REF!
Name Branch: #REF!
Name BU: [4]General!$C$11
Name BU_selected_Country: [1]Macrodata!$D$13
Name BU_selected_Currency: [5]Macrodata!$E$10
Name BU_selected_w_descr: [1]Macrodata!$C$13
Name BUD: #REF!,#REF!,#REF!,#REF!,#REF!,#REF!,#REF!,#REF!,#REF!,#REF!,#REF!,#REF!,#REF!,#REF!,#REF!,#REF!,#REF!,#REF!
Name BUD: #REF!,#REF!,#REF!,#REF!,#REF!,#REF!,#REF!,#REF!,#REF!,#REF!,#REF!,#REF!,#REF!,#REF!,#REF!,#REF!,#REF!,#REF!
Name CHead: IF([2]Sheet1!#REF!=1,[2]Sheet1!#REF!,[2]Sheet1!#REF!)
Name CHead: IF([2]Sheet1!#REF!=1,[2]Sheet1!#REF!,[2]Sheet1!#REF!)
Name COMM_CONS: #REF!
Name COMM_CONS: #REF!
Name COMM_DIV: #REF!
Name COMM_DIV: #REF!
Name CONS_GLB: #REF!
Name CONS_GLB: #REF!
Name Corporate: #REF!
Name Country: [1]General!$C$11
Name Currency: [1]General!$C$12
Name Current_Month: [6]Start!$E$9
Name Data1: IF([2]Sheet1!#REF!=1,[2]Sheet1!#REF!,[2]Sheet1!#REF!)
Name Data1: IF([2]Sheet1!#REF!=1,[2]Sheet1!#REF!,[2]Sheet1!#REF!)
Name Data2: IF([2]Sheet1!#REF!=1,[2]Sheet1!#REF!,[2]Sheet1!#REF!)
Name Data2: IF([2]Sheet1!#REF!=1,[2]Sheet1!#REF!,[2]Sheet1!#REF!)
Name Data3: IF([2]Sheet1!#REF!=1,[2]Sheet1!#REF!,[2]Sheet1!#REF!)
Name Data3: IF([2]Sheet1!#REF!=1,[2]Sheet1!#REF!,[2]Sheet1!#REF!)
Name Data4: IF([2]Sheet1!#REF!=1,[2]Sheet1!#REF!,[2]Sheet1!#REF!)
Name DeptList: #REF!
Name DeptList: #REF!
Name DIVISIONAL_1K: #REF!
Name DIVISIONAL_1K: #REF!
Name Divisions: [3]Data!$U$30:$U$41
Name Divsions: #REF!
Name Divsions: #REF!
Name drop1: #REF!
Name drop1: #REF!

Sheet Individual
A1: Pack Codes | B1: January | C1: February | D1: March | E1: April | F1: May | G1: June | H1: July | I1: August | J1: September | K1: October | L1: November | M1: December | N1: Total | O1: Income Type | P1: Comments
A2: 0425100 - Non Interco Brkg Comm Renewal | B2: ='Renewal book 2026'!J171 | C2: 526071.83 | D2: 850734.25 | E2: ='Renewal book 2026'!M171 | F2: 90142.61 | G2: 483904.91 | H2: 1317800.9 | I2: ='Renewal book 2026'!Q171 | J2: 32133.87 | K2: 927417.03 | L2: 291525.47 | M2: 42412.87 | N2: =SUM(B2:M2) | O2: Renewals -Commission | P2: Linked to renewal book 2025
A3: 0425110 - Brkg Comm New Recurring | C3: 230000 | D3: 0 | E3: 0 | F3: 456683.69 | G3: 180000 | H3: 74000 | I3: 0 | J3: 748234.8 | K3: 100000 | L3: 440734.8 | M3: 234051.09 | N3: =SUM(B3:M3) | O3: New Recurring Business - Commission | P3: Linked to new business and/or cross selling
A4: 0425112 - Brkg Comm New Non-Recurring | O4: New Non Recurring Business - Commission | P4: Linked to new business and/or cross selling
A5: 0425200 - Fees - Standard | O5: Renewals - Fees
A6: 0425210 - Brkg Fees New Recurring | O6: New Recurring Business - Fees | P6: Linked to new business and/or cross selling
A7: 0425212 - Brkg Fees New Non-Recurring | O7: New Non Recurring Business - Fees | P7: Linked to new business and/or cross selling
A8: 0425300 - Fees - Other | O8: Any other Fees | P8: Linked to renewal book 2025
A10: Total | B10: =SUM(B2:B8) | C10: =SUM(C2:C8) | D10: =SUM(D2:D8) | E10: =SUM(E2:E8) | F10: =SUM(F2:F8) | G10: =SUM(G2:G8) | H10: =SUM(H2:H9) | I10: =SUM(I2:I8) | J10: =SUM(J2:J8) | K10: =SUM(K2:K8) | L10: =SUM(L2:L8) | M10: =SUM(M2:M8) | N10: =SUM(N2:N8)

Sheet Renewal book 2026
A1: CLIENT NUMBER | B1: CLIENT NAME | C1: INVOICE NO | D1: INVOICE DATE | E1: INVOICE EFF. DATE | F1: CLIENT PREMUIM | G1: BROKERAGE | H1: SPC FEE | I1: SUBAGENT | J1: January | K1: February | L1: March | M1: April | N1: May | O1: June | P1: July | Q1: August | R1: September | S1: October | T1: November | U1: December | V1: Total | W1: Ctegory
A2: A0223 | B2: Air Botswana | C2: 00297942 | D2: 45324 | E2: 45383 | F2: 14144.74 | G2: 2828.95 | H2: 0 | I2: 0 | M2: 2828.95 | V2: =SUM(J2:U2) | W2: Non Interco Brkg Comm Renewal
A3: A5229 | B3: Alhpa Climbers | U3: 3070.18 | V3: =SUM(J3:U3) | W3: Non Interco Brkg Comm Renewal
A4: A5234 | B4: Another Motsatsi Investments (Pty) Ltd | C4: 00298626 | D4: 45352 | E4: 45352 | F4: 177893.12 | G4: 22236.64 | H4: 0 | I4: 0 | L4: 22236.64 | P4: 34178.55 | V4: =SUM(J4:U4) | W4: Non Interco Brkg Comm Renewal
A5: A4988 | B5: Antya Investment (Pty) Ltd | C5: 00302643 | D5: 45496 | E5: 45474 | F5: 2279.61 | G5: 455.92 | H5: 0 | I5: 0 | P5: 455.92 | V5: =SUM(J5:U5) | W5: Non Interco Brkg Comm Renewal
A6: A2203 | B6: Aon Preservation Fund | S6: 4518 | V6: =SUM(J6:U6) | W6: Non Interco Brkg Comm Renewal
A7: A5077 | B7: Aramex Botswana (Pty) Ltd | C7: 00299411 | D7: 45377 | E7: 45352 | F7: 35198.02 | G7: 4399.75 | H7: 0 | I7: 0 | L7: 19051.47 | V7: =SUM(J7:U7) | W7: Non Interco Brkg Comm Renewal
A8: A0486 | B8: Associated Fund Administrators (Pty) Ltd | Q8: 19980.24 | S8: 130000 | V8: =SUM(J8:U8) | W8: Non Interco Brkg Comm Renewal
A9: A5231 | B9: Astounding Solutions (Pty) Ltd | C9: 00297034 | D9: 45299 | E9: 45292 | F9: 3658.62 | G9: 731.72 | H9: 0 | I9: 0 | J9: 731.72 | K9: 731.72 | L9: 731.72 | M9: 731.72 | N9: 731.72 | O9: 731.72 | P9: 731.72 | Q9: 731.72 | R9: 731.72 | S9: 731.72 | T9: 731.72 | U9: 731.72 | V9: =SUM(J9:U9) | W9: Non Interco Brkg Comm Renewal
A10: E4780 | B10: Barloword Equipment Botswana (Pty) Ltd | C10: 00301163 | D10: 45447 | E10: 45444 | F10: 13596.49 | G10: 2719.3 | H10: 0 | I10: 0 | O10: 262600 | V10: =SUM(J10:U10) | W10: Non Interco Brkg Comm Renewal
A11: B5340 | B11: BIHL Defined Contribution Retirement Fund | C11: 00297961 | D11: 45327 | E11: 45292 | F11: 15131.58 | G11: 3026.32 | H11: 0 | I11: 0 | J11: 3026.32 | V11: =SUM(J11:U11) | W11: Non Interco Brkg Comm Renewal
A12: B5280 | B12: BIHL Insurance Company | C12: 00297856 | D12: 45323 | E12: 45322 | F12: 912.45 | G12: 182.49 | H12: 0 | I12: 0 | Q12: 30852.83 | V12: =SUM(J12:U12) | W12: Non Interco Brkg Comm Renewal
A13: B5447 | B13: BOMaid | C13: 00297740 | D13: 45320 | E13: 45292 | F13: 166027.09 | G13: 33205.42 | H13: 0 | I13: 0 | J13: 56000 | V13: =SUM(J13:U13) | W13: Non Interco Brkg Comm Renewal
A14: B1044 | B14: Botswana Accountancy College | C14: 00297128 | D14: 45301 | E14: 45292 | F14: 508367.69 | G14: 101673.54 | H14: 0 | I14: 0 | J14: 30000 | V14: =SUM(J14:U14) | W14: Non Interco Brkg Comm Renewal
A15: B5253 | B15: Botswana Bureau of Standards | C15: 00299630 | D15: 45390 | E15: 45383 | F15: 13873.99 | G15: 2774.8 | H15: 0 | I15: 0 | M15: 2774.8 | V15: =SUM(J15:U15) | W15: Non Interco Brkg Comm Renewal
A16: B4976 | B16: Botswana Communications Regulatory Authority | C16: 00299802 | D16: 45394 | E16: 45383 | F16: 12105.26 | G16: 2421.05 | H16: 0 | I16: 0 | M16: 2421.05 | V16: =SUM(J16:U16) | W16: Non Interco Brkg Comm Renewal
A17: B5599 | B17: Botswana Energy Regulatory Authority | C17: 00298314 | D17: 45341 | E17: 45323 | F17: 137560.28 | G17: 27512.06 | H17: 0 | I17: 0 | K17: 18223.31 | V17: =SUM(J17:U17) | W17: Non Interco Brkg Comm Renewal
A18: B5074 | B18: Botswana Examinations Council | C18: 00303599 | D18: 45530 | E18: 45505 | F18: 129736.11 | G18: 16217.01 | H18: 0 | I18: 0 | Q18: 98283.34 | V18: =SUM(J18:U18) | W18: Non Interco Brkg Comm Renewal
A19: B5168 | B19: Botswana Housing Corporation Staff Pension Fund | C19: 00299208 | D19: 45372 | E19: 45383 | F19: 8106.34 | G19: 1621.27 | H19: 0 | I19: 0 | M19: 1621.27 | V19: =SUM(J19:U19) | W19: Non Interco Brkg Comm Renewal
A20: B5614 | B20: Botswana Institute for Technology Research and Innovation | C20: 00299531 | D20: 45385 | E20: 45383 | F20: 684867.19 | G20: 136973.44 | H20: 0 | I20: 0 | M20: 100000 | V20: =SUM(J20:U20) | W20: Non Interco Brkg Comm Renewal
A21: B1988 | B21: Botswana Insurance Fund Management | C21: 00302939 | D21: 45506 | E21: 45505 | F21: 138481.02 | G21: 27696.2 | H21: 0 | I21: 0 | Q21: 39187.59 | V21: =SUM(J21:U21) | W21: Non Interco Brkg Comm Renewal
A22: B5211 | B22: Botswana Insurance Holdings Limited | C22: 00303051 | D22: 45510 | E22: 45505 | F22: 150520.2 | G22: 30104.04 | H22: 0 | I22: 0 | Q22: 40858.67 | V22: =SUM(J22:U22) | W22: Non Interco Brkg Comm Renewal
A23: L5011 | B23: Botswana Life Insurance Limited | C23: 00303590 | D23: 45530 | E23: 45505 | F23: 479334.88 | G23: 95866.98 | H23: 0 | I23: 0 | Q23: 123611 | V23: =SUM(J23:U23) | W23: Non Interco Brkg Comm Renewal
A24: B5017 | B24: Botswana Meat Commission | C24: 00301612 | D24: 45460 | E24: 45460 | F24: 6380.17 | G24: 1276.03 | H24: 0 | I24: 0 | O24: 1276.03 | S24: 3301.11 | V24: =SUM(J24:U24) | W24: Non Interco Brkg Comm Renewal
A25: B5367 | B25: Botswana Oil Limited | C25: 00297074 | D25: 45300 | E25: 45205 | F25: 253564.68 | G25: 50712.94 | H25: 0 | I25: 0 | J25: 0 | V25: =SUM(J25:U25) | W25: Non Interco Brkg Comm Renewal
A26: B5301 | B26: Botswana Open University | C26: 00299810 | D26: 45394 | E26: 45383 | F26: 9026.32 | G26: 1805.26 | H26: 0 | I26: 0 | M26: 40000 | V26: =SUM(J26:U26) | W26: Non Interco Brkg Comm Renewal
A27: B5328 | B27: Botswana Postal Services | C27: 00298871 | D27: 45364 | E27: 45383 | F27: 13690.44 | G27: 2738.09 | H27: 0 | I27: 0 | M27: 2738.09 | V27: =SUM(J27:U27) | W27: Non Interco Brkg Comm Renewal
A28: B4858 | B28: Botswana Public Officers Medical Aid Scheme | C28: 00299569 | D28: 45387 | E28: 45383 | F28: 33832.77 | G28: 4229.1 | H28: 0 | I28: 0 | M28: 106216.13 | V28: =SUM(J28:U28) | W28: Non Interco Brkg Comm Renewal
A29: B5288 | B29: Botswana Railways | C29: 00301610 | D29: 45460 | E29: 45383 | F29: 14815.16 | G29: 2963.03 | H29: 0 | I29: 0 | M29: 2963.03 | T29: 0 | V29: =SUM(J29:U29) | W29: Non Interco Brkg Comm Renewal
A30: B4903 | B30: Botswana Stock Exchange | C30: 00297159 | D30: 45302 | E30: 45292 | F30: 103768.35 | G30: 20753.67 | H30: 0 | I30: 0 | J30: 31133.88 | V30: =SUM(J30:U30) | W30: Non Interco Brkg Comm Renewal
A31: B5018 | B31: Botswana Tourism Organization | C31: 00299682 | D31: 45391 | E31: 45383 | F31: 182034.62 | G31: 36406.92 | H31: 0 | I31: 0 | M31: 74390.11 | V31: =SUM(J31:U31) | W31: Non Interco Brkg Comm Renewal
A32: B5464 | B32: Botswana Trade Commission | C32: 00299557 | D32: 45386 | E32: 45383 | F32: 70554.23 | G32: 8819.28 | H32: 0 | I32: 0 | M32: 23570.75 | V32: =SUM(J32:U32) | W32: Non Interco Brkg Comm Renewal
A33: B5735 | B33: BRECKWICK HOLDINGS | C33: 00303034 | D33: 45510 | E33: 45510 | F33: 0 | G33: 0 | H33: 38698.77 | I33: 0 | O33: 30553.26 | V33: =SUM(J33:U33) | W33: Non Interco Brkg Comm Renewal
A34: C4946 | B34: Car Rentals Botswana (Pty) Ltd | C34: 00301188 | D34: 45448 | E34: 45444 | F34: 8596.49 | G34: 1719.3 | H34: 0 | I34: 0 | O34: 27843.07 | V34: =SUM(J34:U34) | W34: Non Interco Brkg Comm Renewal
A35: C5187 | B35: Cash Bazaar Holdings( Pty) Ltd - Industrial Division | C35: 00303473 | D35: 45523 | E35: 45505 | F35: 219298.25 | G35: 43859.65 | H35: 0 | I35: 0 | Q35: 24877.28 | V35: =SUM(J35:U35) | W35: Non Interco Brkg Comm Renewal
A36: C5040 | B36: Cash Bazaar Holdings | C36: 00303449 | D36: 45520 | E36: 45505 | F36: 645124.71 | G36: 129024.94 | H36: 0 | I36: 0 | Q36: 164416.25 | V36: =SUM(J36:U36) | W36: Non Interco Brkg Comm Renewal
A37: C5188 | B37: Cash Bazaar Holdings | C37: 00303452 | D37: 45520 | E37: 45505 | F37: 383887.51 | G37: 76777.5 | H37: 0 | I37: 0 | Q37: 86052.64 | V37: =SUM(J37:U37) | W37: Non Interco Brkg Comm Renewal
A38: H4885 | B38: Cash Bazaar Holdings | C38: 00303456 | D38: 45520 | E38: 45505 | F38: 1153945.7 | G38: 230789.13 | H38: 0 | I38: 0 | Q38: 267951.66 | V38: =SUM(J38:U38) | W38: Non Interco Brkg Comm Renewal
A39: I4667 | B39: Cash Bazaar Holdings | C39: 00303458 | D39: 45520 | E39: 45505 | F39: 197575.66 | G39: 39515.13 | H39: 0 | I39: 0 | Q39: 39515.13 | V39: =SUM(J39:U39) | W39: Non Interco Brkg Comm Renewal
A40: M6904 | B40: Cash Bazaar Holdings | C40: 00303459 | D40: 45520 | E40: 45505 | F40: 204812.58 | G40: 40962.52 | H40: 0 | I40: 0 | Q40: 45129.68 | V40: =SUM(J40:U40) | W40: Non Interco Brkg Comm Renewal
A41: N5019 | B41: Cash Bazaar Holdings | C41: 00303448 | D41: 45520 | E41: 45505 | F41: 180049.38 | G41: 36009.88 | H41: 0 | I41: 0 | Q41: 37796.25 | V41: =SUM(J41:U41) | W41: Non Interco Brkg Comm Renewal
A42: P4976 | B42: Cash Bazaar Holdings | C42: 00303454 | D42: 45520 | E42: 45505 | F42: 136259.65 | G42: 27251.93 | H42: 0 | I42: 0 | Q42: 34033.38 | V42: =SUM(J42:U42) | W42: Non Interco Brkg Comm Renewal
A43: T4978 | B43: Cash Bazaar Holdings | C43: 00303444 | D43: 45520 | E43: 45505 | F43: 166605.04 | G43: 33321.01 | H43: 0 | I43: 0 | Q43: 53278.64 | V43: =SUM(J43:U43) | W43: Non Interco Brkg Comm Renewal
A44: C1433 | B44: Cash Bazaar Holdings (Pty) Ltd | C44: 00303429 | D44: 45520 | E44: 45505 | F44: 5191929.8 | G44: 1038386 | H44: 0 | I44: 0 | Q44: 1527684.9 | V44: =SUM(J44:U44) | W44: Non Interco Brkg Comm Renewal
A45: C5206 | B45: Cashbuild Botswana (Pty) Ltd. | C45: 00302114 | D45: 45476 | E45: 45474 | F45: 64049.01 | G45: 12809.8 | H45: 0 | I45: 0 | P45: 91556.49 | V45: =SUM(J45:U45) | W45: Non Interco Brkg Comm Renewal
A46: C5253 | B46: CB Retail Clothing (Pty) Ltd. | C46: 00303730 | D46: 45533 | E46: 45505 | F46: 160866.46 | G46: 20108.31 | H46: 0 | I46: 0 | Q46: 70637.94 | V46: =SUM(J46:U46) | W46: Non Interco Brkg Comm Renewal
A47: F5003 | B47: The Fields Mall | C47: 00303533 | D47: 45525 | E47: 45527 | F47: 247024.13 | G47: 49404.83 | H47: 0 | I47: 0 | Q47: 49404.83 | V47: =SUM(J47:U47) | W47: Non Interco Brkg Comm Renewal
A48: C5053 | B48: Central Securities Depository of Botswana | C48: 00297481 | D48: 45313 | E48: 45292 | F48: 65855.26 | G48: 13171.05 | H48: 0 | I48: 0 | J48: 18345.9 | V48: =SUM(J48:U48) | W48: Non Interco Brkg Comm Renewal
A49: C5213 | B49: Central Square Body Corporate | U49: 6003 | V49: =SUM(J49:U49) | W49: Non Interco Brkg Comm Renewal
A50: C5138 | B50: CITY LODGE HOTELS LTD | C50: 00302931 | D50: 45505 | E50: 45474 | F50: 39719.99 | G50: 7944 | H50: 0 | I50: 0 | J50: 29706 | K50: 0 | M50: 0 | P50: 29706 | S50: 0 | V50: =SUM(J50:U50) | W50: Non Interco Brkg Comm Renewal
A51: C5029 | B51: Civil Aviation Authority | C51: 00297211 | D51: 45303 | E51: 45287 | F51: 22.53 | G51: 4.51 | H51: 0 | I51: 0 | J51: 307772.26 | M51: 307772.26 | P51: 307772.26 | S51: 307772.26 | V51: =SUM(J51:U51) | W51: Non Interco Brkg Comm Renewal
A52: C5160 | B52: Cletem Electrical (Pty) Ltd | C52: 00302758 | D52: 45502 | E52: 45498 | F52: 123421.05 | G52: 15427.63 | H52: 0 | I52: 0 | P52: 24286.84 | V52: =SUM(J52:U52) | W52: Non Interco Brkg Comm Renewal
A53: C5280 | B53: Coca Cola Beverages Manufaturing | C53: 00298529 | D53: 45350 | E53: 45281 | F53: 1398.98 | G53: 174.87 | H53: 0 | I53: 0 | J53: 553818.03 | V53: =SUM(J53:U53) | W53: Non Interco Brkg Comm Renewal
A54: C5260 | B54: Consulting Unlimited (Pty) Ltd | C54: 00297516 | D54: 45314 | E54: 45314 | F54: 5701.75 | G54: 570.18 | H54: 0 | I54: 0 | J54: 587.72 | V54: =SUM(J54:U54) | W54: Non Interco Brkg Comm Renewal
A55: C5278 | B55: Cotton on Botswana (Pty) Ltd | C55: 00297818 | D55: 45323 | E55: 45261 | F55: 90427.13 | G55: 18085.43 | H55: 0 | I55: 0 | J55: 0 | U55: 18085.43 | V55: =SUM(J55:U55) | W55: Non Interco Brkg Comm Renewal
A56: C0847 | B56: Cresta Group | C56: 00297690 | D56: 45320 | E56: 45292 | F56: 3083879.3 | G56: 616775.86 | H56: 0 | I56: 0 | J56: 174536.91 | M56: 174536.91 | P56: 174536.91 | S56: 174536.91 | V56: =SUM(J56:U56) | W56: Non Interco Brkg Comm Renewal
A57: C4980 | B57: Crowsley Park (Pty)Ltd | C57: 00298955 | D57: 45365 | E57: 45352 | F57: 9802.63 | G57: 1225.33 | H57: 0 | I57: 0 | L57: 5276.32 | V57: =SUM(J57:U57) | W57: Non Interco Brkg Comm Renewal
A58: C4873 | B58: Cummins Botswana (Pty) Ltd | C58: 00302911 | D58: 45505 | E58: 45505 | F58: 156257.29 | G58: 19532.16 | H58: 0 | I58: 0 | Q58: 35354.91 | V58: =SUM(J58:U58) | W58: Non Interco Brkg Comm Renewal
A59: D5202 | B59: Deferred Pensioners Pension Fund | C59: 00299513 | D59: 45385 | E59: 45383 | F59: 9210.53 | G59: 1842.11 | H59: 0 | I59: 0 | M59: 1842.11 | V59: =SUM(J59:U59) | W59: Non Interco Brkg Comm Renewal
A60: D5115 | B60: Deloitte & Touche | C60: 00301315 | D60: 45453 | E60: 45444 | F60: 239982.46 | G60: 47996.49 | H60: 0 | I60: 0 | O60: 41459.08 | V60: =SUM(J60:U60) | W60: Non Interco Brkg Comm Renewal
A61: D2022 | B61: DHL International (Botswana) Pty Ltd | C61: 00297225 | D61: 45303 | E61: 45292 | F61: 48801.45 | G61: 9760.29 | H61: 0 | I61: 0 | J61: 19807.09 | V61: =SUM(J61:U61) | W61: Non Interco Brkg Comm Renewal
A62: D5195 | B62: Dimension Data (Pty) Ltd | C62: 00300239 | D62: 45406 | E62: 45383 | F62: 24951.53 | G62: 0 | H62: 0 | I62: 0 | M62: 91255.91 | V62: =SUM(J62:U62) | W62: Non Interco Brkg Comm Renewal
A63: D4940 | B63: Dirwe (Pty) Ltd | C63: 00302647 | D63: 45496 | E63: 45474 | F63: 446.27 | G63: 89.25 | H63: 0 | I63: 0 | P63: 89.25 | V63: =SUM(J63:U63) | W63: Non Interco Brkg Comm Renewal
A64: D0926 | B64: Dulux Botswana (Pty) Ltd | C64: 00297497 | D64: 45313 | E64: 45292 | F64: 274493.74 | G64: 54898.75 | H64: 0 | I64: 0 | J64: 97463.98 | V64: =SUM(J64:U64) | W64: Non Interco Brkg Comm Renewal
A65: E4809 | B65: East Coast Investors (Pty) Ltd | C65: 00301139 | D65: 45446 | E65: 45444 | F65: 53299.21 | G65: 10659.84 | H65: 0 | I65: 0 | O65: 11680.94 | V65: =SUM(J65:U65) | W65: Non Interco Brkg Comm Renewal
A66: E4822 | B66: Exploration Geophysics | S66: 1991 | V66: =SUM(J66:U66) | W66: Non Interco Brkg Comm Renewal
A67: F4993 | B67: Filano (Pty) Ltd | C67: 00300949 | D67: 45439 | E67: 45413 | F67: 50368.42 | G67: 10073.68 | H67: 0 | I67: 0 | K67: 35000 | N67: 35000 | Q67: 35000 | T67: 35000 | V67: =SUM(J67:U67) | W67: Non Interco Brkg Comm Renewal
A68: F5017 | B68: Franklin Electricals | Q68: 50000 | V68: =SUM(J68:U68) | W68: Non Interco Brkg Comm Renewal
A69: F4956 | B69: Free Standing Additional Voluntary Contributions Retirement Fund | C69: 00302031 | D69: 45475 | E69: 45474 | F69: 10542.32 | G69: 2108.46 | H69: 0 | I69: 0 | P69: 2108.46 | V69: =SUM(J69:U69) | W69: Non Interco Brkg Comm Renewal
A70: G1325 | B70: G4 Consulting Engineers | C70: 00298079 | D70: 45334 | E70: 45352 | F70: 55207.95 | G70: 5520.8 | H70: 0 | I70: 0 | L70: 27802.61 | V70: =SUM(J70:U70) | W70: Non Interco Brkg Comm Renewal
A71: G5319 | B71: GENERAL PACKAGING INDUSTRIES (PTY) LTD | S71: 25692 | V71: =SUM(J71:U71) | W71: Non Interco Brkg Comm Renewal
A72: G | B72: General Dynamics | J72: 3000 | V72: =SUM(J72:U72) | W72: Non Interco Brkg Comm Renewal
A73: M6284 | B73: Goo Moremi Resort (Pty) Ltd | C73: 00299722 | D73: 45392 | E73: 45383 | F73: 191616.72 | G73: 38323.34 | H73: 0 | I73: 0 | M73: 43959.79 | V73: =SUM(J73:U73) | W73: Non Interco Brkg Comm Renewal
A74: G5373 | B74: Grips Energy Botswana Proprietary Limited | C74: 00303039 | D74: 45510 | E74: 45505 | F74: 30030.76 | G74: 6006.15 | H74: 0 | I74: 0 | Q74: 6006.15 | V74: =SUM(J74:U74) | W74: Non Interco Brkg Comm Renewal
A75: I4636 | B75: Italtswana Construction Company | C75: 00302644 | D75: 45496 | E75: 45474 | F75: 11341.29 | G75: 2268.26 | H75: 0 | I75: 0 | P75: 3830.76 | V75: =SUM(J75:U75) | W75: Non Interco Brkg Comm Renewal
A76: A4913 | B76: Kalideck Botswana (Pty)Ltd | C76: 00297050 | D76: 45299 | E76: 45292 | F76: 15406.15 | G76: 1925.77 | H76: 0 | I76: 0 | J76: 12144.09 | V76: =SUM(J76:U76) | W76: Non Interco Brkg Comm Renewal
A77: K1800 | B77: Kgalagadi Breweries (Pty) Ltd | C77: 00299301 | D77: 45376 | E77: 45383 | F77: 956123.96 | G77: 0 | H77: 0 | I77: 0 | M77: 58000 | V77: =SUM(J77:U77) | W77: Non Interco Brkg Comm Renewal
A78: K5292 | B78: Kgale Close | C78: 00299301 | D78: 45376 | E78: 45383 | F78: 956123.96 | G78: 0 | H78: 0 | I78: 0 | T78: 3716 | V78: =SUM(J78:U78) | W78: Non Interco Brkg Comm Renewal
A79: K5060 | B79: Kweneng Commercial Consultants (Pty) Ltd | C79: 00297849 | D79: 45323 | E79: 45323 | F79: 23174.34 | G79: 4634.87 | H79: 0 | I79: 0 | K79: 19616.22 | V79: =SUM(J79:U79) | W79: Non Interco Brkg Comm Renewal
A80: L4963 | B80: Legae English Medium School (Pty) Ltd | C80: 00297822 | D80: 45323 | E80: 45323 | F80: -217227.19 | G80: -27153.4 | H80: 0 | I80: 0 | K80: 49977.63 | V80: =SUM(J80:U80) | W80: Non Interco Brkg Comm Renewal
A81: L5194 | B81: Lepokole Project | C81: 00299725 | D81: 45392 | E81: 45383 | F81: 31843.3 | G81: 6368.66 | H81: 0 | I81: 0 | M81: 9896.38 | V81: =SUM(J81:U81) | W81: Non Interco Brkg Comm Renewal
A82: L5098 | B82: Letlole La Rona | C82: 00301885 | D82: 45469 | E82: 45474 | F82: 565966.51 | G82: 113193.3 | H82: 0 | I82: 0 | P82: 161464.43 | V82: =SUM(J82:U82) | W82: Non Interco Brkg Comm Renewal
A83: L5155 | B83: Letshego Holdings Limited | C83: 00297482 | D83: 45313 | E83: 45292 | F83: 18157.02 | G83: 2269.63 | H83: 0 | I83: 0 | J83: 169649.4 | M83: 169649.4 | P83: 169649.4 | S83: 169649.4 | V83: =SUM(J83:U83) | W83: Non Interco Brkg Comm Renewal
A84: L5040 | B84: Lotsane Complex (Pty) Ltd | C84: 00302641 | D84: 45496 | E84: 45474 | F84: 15710.9 | G84: 3142.18 | H84: 0 | I84: 0 | P84: 3142.18 | V84: =SUM(J84:U84) | W84: Non Interco Brkg Comm Renewal
A85: M7296 | B85: Manprop Body Corporate | C85: 00297752 | D85: 45320 | E85: 45292 | F85: 55500.57 | G85: 11100.11 | H85: 0 | I85: 0 | J85: 11100.11 | V85: =SUM(J85:U85) | W85: Non Interco Brkg Comm Renewal
A86: M7728 | B86: MARGUERITE HOLDINGS (PTY) LTD | C86: 00298604 | D86: 45352 | E86: 45471 | F86: 6900.59 | G86: 1380.12 | H86: 0 | I86: 0 | O86: 1380.12 | V86: =SUM(J86:U86) | W86: Non Interco Brkg Comm Renewal
A87: M5521 | B87: Maru A Pula School | C87: 00299614 | D87: 45387 | E87: 45387 | F87: 582.62 | G87: 116.52 | H87: 0 | I87: 0 | J87: 79307.97 | M87: 0 | V87: =SUM(J87:U87) | W87: Non Interco Brkg Comm Renewal
A88: M7245 | B88: Metropolitan Staff Pension Fund | C88: 00300063 | D88: 45401 | E88: 45383 | F88: 7101.75 | G88: 1420.35 | H88: 0 | I88: 0 | M88: 1693.23 | V88: =SUM(J88:U88) | W88: Non Interco Brkg Comm Renewal
A89: M7399 | B89: Metropolitan Staff Provident Fund | C89: 00300064 | D89: 45401 | E89: 45383 | F89: 7101.75 | G89: 1420.35 | H89: 0 | I89: 0 | M89: 1420.35 | V89: =SUM(J89:U89) | W89: Non Interco Brkg Comm Renewal
A90: M7314 | B90: Millenium Pension Fund | C90: 00302009 | D90: 45470 | E90: 45474 | F90: 107277.71 | G90: 21455.54 | H90: 0 | I90: 0 | P90: 21455.54 | V90: =SUM(J90:U90) | W90: Non Interco Brkg Comm Renewal
A91: M5457 | B91: Minchin & Kelly (Botswana) | C91: 00301756 | D91: 45463 | E91: 45474 | F91: 107338.26 | G91: 10733.83 | H91: 0 | I91: 0 | P91: 10733.83 | V91: =SUM(J91:U91) | W91: Non Interco Brkg Comm Renewal
A92: G5258 | B92: Minet Beneficiary Fund | C92: 00303655 | D92: 45532 | E92: 45474 | F92: 6419.74 | G92: 1283.95 | H92: 0 | I92: 0 | P92: 1283.95 | V92: =SUM(J92:U92) | W92: Non Interco Brkg Comm Renewal
A93: A1987 | B93: Minet Botswana (Pty)Ltd | C93: 00297724 | D93: 45320 | E93: 45292 | F93: 39473.68 | G93: 7894.74 | H93: 0 | I93: 0 | J93: 320103.52 | V93: =SUM(J93:U93) | W93: Non Interco Brkg Comm Renewal
A94: M8158 | B94: Minet Retirement Solutions | J94: 168682.05 | K94: timming | V94: =SUM(J94:U94) | W94: Non Interco Brkg Comm Renewal
A95: M8160 | B95: Minet Risk Management & Consulting | J95: 8601.47 | L95: timming | V95: =SUM(J95:U95) | W95: Non Interco Brkg Comm Renewal
A96: M7729 | B96: MONARDA HOLDINGS (PTY) LTD | O96: 577.31 | S96: 577 | V96: =SUM(J96:U96) | W96: Non Interco Brkg Comm Renewal
A97: M6784 | B97: Moremi Air Services ( Pty) Ltd | C97: 00303037 | D97: 45510 | E97: 45505 | F97: 5424685.9 | G97: 813702.89 | H97: 0 | I97: 0 | Q97: 1396174.3 | V97: =SUM(J97:U97) | W97: Non Interco Brkg Comm Renewal
A98: M1811 | B98: MRI Botswana Limited | C98: 00297059 | D98: 45300 | E98: 45292 | F98: 133501.16 | G98: 26700.23 | H98: 0 | I98: 0 | J98: 39374.27 | V98: =SUM(J98:U98) | W98: Non Interco Brkg Comm Renewal
A99: M6790 | B99: Multichoice Botswana (Pty) Ltd | C99: 00302927 | D99: 45505 | E99: 45505 | F99: 134923.5 | G99: 26984.7 | H99: 0 | I99: 0 | Q99: 102439.88 | V99: =SUM(J99:U99) | W99: Non Interco Brkg Comm Renewal
A100: N5238 | B100: Nafprop (Proprietary) Limited | C100: 00299092 | D100: 45370 | E100: 45379 | F100: 37372.26 | G100: 7474.45 | H100: 0 | I100: 0 | L100: 7474.45 | V100: =SUM(J100:U100) | W100: Non Interco Brkg Comm Renewal
...

Sheet Revenue walk Retail
A1: Revenue walk
A2: AON GROUP excl Exit | R2: Plug in Retail headoffice cost centre
A3: =SIB_Retail_details_R!B28 | B3: =SIB_Retail_details_R!C28 | E3: =SUM(C5:E5) | J3: =SUM(F5:J5) | Q3: =SUM(P5:Q5)
A4: ='[14]Revenue walk (Brk)'!A4 | C4: =SIB_Retail_details_R!C10 | D4: =SIB_Retail_details_R!C9 | E4: =SIB_Retail_details_R!C8 | F4: =SIB_Retail_details_R!C3 | G4: =SIB_Retail_details_R!C4 | H4: =SIB_Retail_details_R!C7 | I4: =SIB_Retail_details_R!C5 | J4: =SIB_Retail_details_R!C6 | R4: =CONCATENATE(A3," 2017"," update")
A5: =SIB_Retail_details_R!D28 | C5: =VLOOKUP(C4,SIB_Retail_details_R!$C$3:$E$17,3,FALSE) | D5: =VLOOKUP(D4,SIB_Retail_details_R!$C$3:$E$17,3,FALSE) | E5: =VLOOKUP(E4,SIB_Retail_details_R!$C$3:$E$17,3,FALSE) | F5: =VLOOKUP(F4,SIB_Retail_details_R!$C$3:$E$17,3,FALSE) | G5: =VLOOKUP(G4,SIB_Retail_details_R!$C$3:$E$17,3,FALSE) | H5: =VLOOKUP(H4,SIB_Retail_details_R!$C$3:$E$17,3,FALSE) | I5: =VLOOKUP(I4,SIB_Retail_details_R!$C$3:$E$17,3,FALSE) | J5: =VLOOKUP(J4,SIB_Retail_details_R!$C$3:$E$17,3,FALSE) | R5: =SIB_Retail_details_R!E28 | S5: =SUM(A5:Q5)-R5
A9: =A4 | B9: =A5
A10: =C4 | B10: =C5
A11: =D4 | B11: =D5
A12: =E4 | B12: =E5
A13: =F4 | B13: =F5
A14: =G4 | B14: =G5
A15: =H4 | B15: =H5
A16: =I4 | B16: =I5
A17: =J4 | B17: =J5
A18: =R4 | B18: =R5 | C18: =SUM(B9:B17)-B18
B24: Claims Outsourced | C24: New new positions
B25: Retail Restructure | C25: Replacement positions
B26: Broking Restructure | C26: Employee transfers
B27: CFC out

Sheet SIB_Retail_details_R
D2: Headcount | E2: Value
C3: NET EMPLOYEE TRANSFERS | E3: =SUMIF(J:J,C3,F:F)
C4: NET SALARY CHANGES | E4: =SUMIF(J:J,C4,F:F)
C5: NEW POSITIONS '16 | E5: =SUMIF(J:J,C5,F:F)
C6: NEW POSITIONS '17 | E6: =SUMIF(J:J,C6,F:F)
C7: REPLACEMENTS '16 | E7: =SUMIF(J:J,C7,F:F)
C8: RESTRUCTURING '16 | E8: =SUMIF(J:J,C8,F:F)
B9: Add further details here | C9: SEPARATIONS - INVOLUNTARY | E9: =SUMIF(J:J,C9,F:F)
C10: SEPARATIONS - VOLUNTARY | E10: =SUMIF(J:J,C10,F:F)
E11: =SUMIF(J:J,C11,F:F)
A18: [Begin Format Range] | G18: aon prd:Payroll
A19: 0 | G19: 2016
A20: 1 | G20: Annual
A21: 2 | G21: Actual
A22: 3 | G22: unspecified department
A23: D
A24: N
A25: [End Format Range]
B26: aon prd:Payroll:1
B28: RETAIL | C28: 2016 - 2017 | D28: =SUM(D$34:D$1048576) | E28: =SUM(E$34:E$1048576) | F28: =SUM(F$34:F$1048576)
D30: dec YTD | E30: dec YTD
B31: Department | C31: EE | D31: 42370.083 | E31: 42736.083
D32: Working Forecast | E32: Working Budget
B33: =B31 | C33: =C31 | D33: TMP Perm | E33: Permanent TCTC | F33: Variance | G33: Start Date | H33: Termination Date | I33: Group | J33: Reasons
A34: N | B34: 67891 - Hewitt McLagan | C34: 263313 - TYRONE BRUCE JANSEN | G34: 20140901 | J34: =IFERROR(VLOOKUP(C34,Lynette!$C$13:$D$1213,2,FALSE),0) | K34: =E34/D34-1
A35: N | B35: 67852 - Healthcare Operations | C35: 120102 - CLAUDIA LAHOUD | G35: 19950201 | J35: =IFERROR(VLOOKUP(C35,Lynette!$C$13:$D$1213,2,FALSE),0) | K35: =E35/D35-1
A36: N | B36: 67852 - Healthcare Operations | C36: 140502 - JACQUELINE NEL | G36: 19910601 | J36: =IFERROR(VLOOKUP(C36,Lynette!$C$13:$D$1213,2,FALSE),0) | K36: =E36/D36-1
A37: N | B37: 67852 - Healthcare Operations | C37: 262434 - ANNAKE PEARCE | G37: 20120401 | J37: =IFERROR(VLOOKUP(C37,Lynette!$C$13:$D$1213,2,FALSE),0) | K37: =E37/D37-1
A38: N | B38: 67852 - Healthcare Operations | C38: 262608 - GAVIN JOHN GRIFFIN | G38: 20130102 | J38: =IFERROR(VLOOKUP(C38,Lynette!$C$13:$D$1213,2,FALSE),0) | K38: =E38/D38-1
A39: N | B39: 67853 - Healthcare Bloemfontein | C39: 220537 - ANILIA BOSHOFF | G39: 20090401 | J39: =IFERROR(VLOOKUP(C39,Lynette!$C$13:$D$1213,2,FALSE),0) | K39: =E39/D39-1
A40: N | B40: 67853 - Healthcare Bloemfontein | C40: 220554 - HELEN VAN HEERDEN | G40: 20110201 | J40: =IFERROR(VLOOKUP(C40,Lynette!$C$13:$D$1213,2,FALSE),0) | K40: =E40/D40-1
A41: N | B41: 67853 - Healthcare Bloemfontein | C41: 263195 - LEONIE FOURIE | G41: 20140501 | J41: =IFERROR(VLOOKUP(C41,Lynette!$C$13:$D$1213,2,FALSE),0) | K41: =E41/D41-1
A42: N | B42: 67854 - Healthcare Cape Town | C42: 220110 - MARGAUX VAN HUYSSTEEN | G42: 20010618 | J42: =IFERROR(VLOOKUP(C42,Lynette!$C$13:$D$1213,2,FALSE),0) | K42: =E42/D42-1
A43: N | B43: 67854 - Healthcare Cape Town | C43: 260001 - VALENTINO YOUNG | G43: 20090316 | J43: =IFERROR(VLOOKUP(C43,Lynette!$C$13:$D$1213,2,FALSE),0) | K43: =E43/D43-1
A44: N | B44: 67854 - Healthcare Cape Town | C44: 263398 - ANTON EUGENE FOSTER | G44: 20141223 | J44: =IFERROR(VLOOKUP(C44,Lynette!$C$13:$D$1213,2,FALSE),0) | K44: =E44/D44-1
A45: N | B45: 67854 - Healthcare Cape Town | C45: 263625 - PORTIA LINN MOEN | G45: 20151101 | J45: =IFERROR(VLOOKUP(C45,Lynette!$C$13:$D$1213,2,FALSE),0) | K45: =E45/D45-1
... A47: N | B47: 67854 - Healthcare Cape Town | C47: 61821 - CHANTEL FRITZ | G47: 20110101 | J47: =IFERROR(VLOOKUP(C47,Lynette!$C$13:$D$1213,2,FALSE),0) | K47: =E47/D47-1
A48: N | B48: 67854 - Healthcare Cape Town | C48: New 1 | J48: =IFERROR(VLOOKUP(C48,Lynette!$C$13:$D$1213,2,FALSE),0) | K48: =E48/D48-1
A49: N | B49: 67855 - Healthcare Durban | C49: 130307 - LUTHANDO MRWEBI | G49: 20110301 | H49: 20160520 | J49: =IFERROR(VLOOKUP(C49,Lynette!$C$13:$D$1213,2,FALSE),0) | K49: =E49/D49-1
A50: N | B50: 67855 - Healthcare Durban | C50: 161800 - FRANK ADRIAN PREEN | G50: 20060223 | J50: =IFERROR(VLOOKUP(C50,Lynette!$C$13:$D$1213,2,FALSE),0) | K50: =E50/D50-1
A51: N | B51: 67855 - Healthcare Durban | C51: 190172 - CATERINE CECILIA SINGH | G51: 20100301 | J51: =IFERROR(VLOOKUP(C51,Lynette!$C$13:$D$1213,2,FALSE),0) | K51: =E51/D51-1
A52: N | B52: 67855 - Healthcare Durban | C52: 20164 - MARIANET BREYTENBACH | G52: 20101001 | J52: =IFERROR(VLOOKUP(C52,Lynette!$C$13:$D$1213,2,FALSE),0) | K52: =E52/D52-1
A53: N | B53: 67855 - Healthcare Durban | C53: 263441 - DHANASAGERI KUPPUSAMY | G53: 20150302 | J53: =IFERROR(VLOOKUP(C53,Lynette!$C$13:$D$1213,2,FALSE),0) | K53: =E53/D53-1
A54: N | B54: 67855 - Healthcare Durban | C54: 263706 - NKULULEKO GLADWELL SIBISI | G54: 20160601 | J54: =IFERROR(VLOOKUP(C54,Lynette!$C$13:$D$1213,2,FALSE),0) | K54: =E54/D54-1
A55: N | B55: 67855 - Healthcare Durban | C55: 263724 - THOLINHLANHLA ANDILE DLAMINI | G55: 20160701 | J55: =IFERROR(VLOOKUP(C55,Lynette!$C$13:$D$1213,2,FALSE),0) | K55: =E55/D55-1
A56: N | B56: 67855 - Healthcare Durban | C56: 71509 - KEVANDHREE KADY GOVENDER | G56: 20040920 | J56: =IFERROR(VLOOKUP(C56,Lynette!$C$13:$D$1213,2,FALSE),0) | K56: =E56/D56-1
A57: N | B57: 67855 - Healthcare Durban | C57: New 1 | J57: =IFERROR(VLOOKUP(C57,Lynette!$C$13:$D$1213,2,FALSE),0) | K57: =E57/D57-1
A58: N | B58: 67856 - Healthcare Port Elizabeth | C58: 21510 - CHARMAINE VAN ECK | G58: 19930701 | J58: =IFERROR(VLOOKUP(C58,Lynette!$C$13:$D$1213,2,FALSE),0) | K58: =E58/D58-1
A59: N | B59: 67856 - Healthcare Port Elizabeth | C59: 262957 - AREESH SATAAR | G59: 20131001 | J59: =IFERROR(VLOOKUP(C59,Lynette!$C$13:$D$1213,2,FALSE),0) | K59: =E59/D59-1
A60: N | B60: 67856 - Healthcare Port Elizabeth | C60: 263504 - NTOMBOXOLO EUGENIA STEMELE | G60: 20150504 | J60: =IFERROR(VLOOKUP(C60,Lynette!$C$13:$D$1213,2,FALSE),0) | K60: =E60/D60-1
A61: N | B61: 67856 - Healthcare Port Elizabeth | C61: 263756 - ZWELITHA TSHITHIZA | G61: 20160915 | J61: =IFERROR(VLOOKUP(C61,Lynette!$C$13:$D$1213,2,FALSE),0) | K61: =E61/D61-1
A62: N | B62: 67856 - Healthcare Port Elizabeth | C62: New 1 | J62: =IFERROR(VLOOKUP(C62,Lynette!$C$13:$D$1213,2,FALSE),0) | K62: =E62/D62-1
A63: N | B63: 67857 - Healthcare Pretoria | C63: 220114 - GERTRUIDA PETRONELLA VAN DER RYST | G63: 20050801 | J63: =IFERROR(VLOOKUP(C63,Lynette!$C$13:$D$1213,2,FALSE),0) | K63: =E63/D63-1
A64: N | B64: 67857 - Healthcare Pretoria | C64: 263745 - WAYNE BOJé | G64: 20160901 | J64: =IFERROR(VLOOKUP(C64,Lynette!$C$13:$D$1213,2,FALSE),0) | K64: =E64/D64-1
A65: N | B65: 67857 - Healthcare Pretoria | C65: 50402 - BRUCE ANDREW EDWARDS | G65: 20050201 | J65: =IFERROR(VLOOKUP(C65,Lynette!$C$13:$D$1213,2,FALSE),0) | K65: =E65/D65-1
B66: 67857 - Healthcare Pretoria | C66: 61812 - ROXANNE SHARON VON ABO | G66: 20090112 | J66: =IFERROR(VLOOKUP(C66,Lynette!$C$13:$D$1213,2,FALSE),0) | K66: 1
A67: N | B67: 67857 - Healthcare Pretoria | C67: 61821 - CHANTEL FRITZ | G67: 20110101 | J67: =IFERROR(VLOOKUP(C67,Lynette!$C$13:$D$1213,2,FALSE),0) | K67: =E67/D67-1
A68: N | B68: 67858 - Health Risk Management | C68: 151608 - CHRISTINE CHARLOTTE OOSTHUIZEN | G68: 20090201 | J68: =IFERROR(VLOOKUP(C68,Lynette!$C$13:$D$1213,2,FALSE),0) | K68: =E68/D68-1
A69: N | B69: 67860 - Healthcare Sales | C69: 263747 - GAVIN ROBERTS | G69: 20160912 | J69: =IFERROR(VLOOKUP(C69,Lynette!$C$13:$D$1213,2,FALSE),0) | K69: =E69/D69-1
A70: N | B70: 67860 - Healthcare Sales | C70: New 1 | J70: =IFERROR(VLOOKUP(C70,Lynette!$C$13:$D$1213,2,FALSE),0) | K70: =E70/D70-1
A71: N | B71: 67860 - Healthcare Sales | C71: New 3 | J71: =IFERROR(VLOOKUP(C71,Lynette!$C$13:$D$1213,2,FALSE),0) | K71: =E71/D71-1
A72: N | B72: 67862 - Service SSC | C72: 11411 - SHAAHIDA ADAMS | G72: 20090406 | J72: =IFERROR(VLOOKUP(C72,Lynette!$C$13:$D$1213,2,FALSE),0) | K72: =E72/D72-1
A73: N | B73: 67862 - Service SSC | C73: 230528 - JOHANNES BAREND WOLMARANS | G73: 20100706 | J73: =IFERROR(VLOOKUP(C73,Lynette!$C$13:$D$1213,2,FALSE),0) | K73: =E73/D73-1
A74: N | B74: 67862 - Service SSC | C74: 262854 - HILARY FLORENCE LOCK | G74: 20130617 | J74: =IFERROR(VLOOKUP(C74,Lynette!$C$13:$D$1213,2,FALSE),0) | K74: =E74/D74-1
A75: N | B75: 67862 - Service SSC | C75: 263377 - CHARLENE ERIKA FLEISCHER | G75: 20150105 | J75: =IFERROR(VLOOKUP(C75,Lynette!$C$13:$D$1213,2,FALSE),0) | K75: =E75/D75-1
A76: N | B76: 67862 - Service SSC | C76: 263689 - MUHAMMED-KHALID ALI JORDAAN | G76: 20160329 | J76: =IFERROR(VLOOKUP(C76,Lynette!$C$13:$D$1213,2,FALSE),0) | K76: =E76/D76-1
A77: N | B77: 67863 - Healthcare Team1 | C77: 220118 - DEIDRE MARX | G77: 20060123 | J77: =IFERROR(VLOOKUP(C77,Lynette!$C$13:$D$1213,2,FALSE),0) | K77: =E77/D77-1
A78: N | B78: 67863 - Healthcare Team1 | C78: 262309 - NGOAKO JOSLINAH HEYMANN | G78: 20111024 | J78: =IFERROR(VLOOKUP(C78,Lynette!$C$13:$D$1213,2,FALSE),0) | K78: =E78/D78-1
A79: N | B79: 67863 - Healthcare Team1 | C79: 262533 - ASHLEY BALDWIN ADAMS | G79: 20120901 | J79: =IFERROR(VLOOKUP(C79,Lynette!$C$13:$D$1213,2,FALSE),0) | K79: =E79/D79-1
B80: 67863 - Healthcare Team1 | C80: 262648 - ARON SIPHO MNISI | G80: 20130201 | J80: =IFERROR(VLOOKUP(C80,Lynette!$C$13:$D$1213,2,FALSE),0) | K80: =E80/D80-1
A81: N | B81: 67865 - Healthcare Team3 | C81: 120110 - CELESTE AQUALINE LAWRENCE | G81: 20060701 | J81: =IFERROR(VLOOKUP(C81,Lynette!$C$13:$D$1213,2,FALSE),0) | K81: =E81/D81-1
A82: N | B82: 67865 - Healthcare Team3 | C82: 151601 - BRENDA OPPERMAN | G82: 20000104 | J82: =IFERROR(VLOOKUP(C82,Lynette!$C$13:$D$1213,2,FALSE),0) | K82: =E82/D82-1
A83: N | B83: 67865 - Healthcare Team3 | C83: 190134 - CAREN SWANEPOEL | G83: 20081101 | J83: =IFERROR(VLOOKUP(C83,Lynette!$C$13:$D$1213,2,FALSE),0) | K83: =E83/D83-1
A84: N | B84: 67865 - Healthcare Team3 | C84: 70136 - VINODHA SELEENA GOVENDER | G84: 20110207 | J84: =IFERROR(VLOOKUP(C84,Lynette!$C$13:$D$1213,2,FALSE),0) | K84: =E84/D84-1
A85: N | B85: 67866 - Healthcare Team4 | C85: 11403 - YUNUS ANIFF | G85: 20080401 | J85: =IFERROR(VLOOKUP(C85,Lynette!$C$13:$D$1213,2,FALSE),0) | K85: =E85/D85-1
A86: N | B86: 67866 - Healthcare Team4 | C86: 190166 - JODI SHULMAN | G86: 20100118 | J86: =IFERROR(VLOOKUP(C86,Lynette!$C$13:$D$1213,2,FALSE),0) | K86: =E86/D86-1
A87: N | B87: 67866 - Healthcare Team4 | C87: 262547 - MERVIN ANDERSON | G87: 20121022 | J87: =IFERROR(VLOOKUP(C87,Lynette!$C$13:$D$1213,2,FALSE),0) | K87: 1
A88: N | B88: 67866 - Healthcare Team4 | C88: 263744 - FIRDAUS SOOMAR | G88: 20160901 | J88: =IFERROR(VLOOKUP(C88,Lynette!$C$13:$D$1213,2,FALSE),0) | K88: =E88/D88-1
A89: N | B89: 67866 - Healthcare Team4 | C89: 30821 - JANETTE SUSAN CLARK | G89: 20080825 | J89: =IFERROR(VLOOKUP(C89,Lynette!$C$13:$D$1213,2,FALSE),0) | K89: =E89/D89-1
A90: N | B90: 67866 - Healthcare Team4 | C90: 61822 - LEE CATHERINE FRASER | G90: 20110201 | H90: 20160630 | J90: =IFERROR(VLOOKUP(C90,Lynette!$C$13:$D$1213,2,FALSE),0) | K90: =E90/D90-1
A91: N | B91: 67866 - Healthcare Team4 | C91: New 1 | J91: =IFERROR(VLOOKUP(C91,Lynette!$C$13:$D$1213,2,FALSE),0) | K91: =E91/D91-1
A92: N | B92: 67866 - Healthcare Team4 | C92: New 2 | J92: =IFERROR(VLOOKUP(C92,Lynette!$C$13:$D$1213,2,FALSE),0) | K92: =E92/D92-1
A93: N | B93: 67861 - Service ARC | C93: 11403 - YUNUS ANIFF | G93: 20080401 | J93: =IFERROR(VLOOKUP(C93,Lynette!$C$13:$D$1213,2,FALSE),0) | K93: =E93/D93-1
A94: N | B94: 67861 - Service ARC | C94: 200806 - AMANDA CELESTE THINNIES | G94: 20011101 | J94: =IFERROR(VLOOKUP(C94,Lynette!$C$13:$D$1213,2,FALSE),0) | K94: =E94/D94-1
A95: N | B95: 67861 - Service ARC | C95: 20170 - MARGARETHA ELAINE BROODRYK | G95: 20110601 | J95: =IFERROR(VLOOKUP(C95,Lynette!$C$13:$D$1213,2,FALSE),0) | K95: =E95/D95-1
A96: N | B96: 67861 - Service ARC | C96: 262410 - ABEDAH CHASULWA MUSENGI | G96: 20120301 | J96: =IFERROR(VLOOKUP(C96,Lynette!$C$13:$D$1213,2,FALSE),0) | K96: =E96/D96-1
A97: N | B97: 67861 - Service ARC | C97: 262532 - NEO GIVEN MOHOLISA | G97: 20120903 | H97: 20160610 | J97: =IFERROR(VLOOKUP(C97,Lynette!$C$13:$D$1213,2,FALSE),0) | K97: =E97/D97-1
A98: N | B98: 67861 - Service ARC | C98: 262642 - KENEILWE CATHERINE LEEUW | G98: 20130201 | J98: =IFERROR(VLOOKUP(C98,Lynette!$C$13:$D$1213,2,FALSE),0) | K98: =E98/D98-1
B99: 67861 - Service ARC | C99: 262959 - LOIS CATHLEEN JOHNSON | G99: 20131001 | H99: 20160219 | J99: =IFERROR(VLOOKUP(C99,Lynette!$C$13:$D$1213,2,FALSE),0) | K99: 1
A100: N | B100: 67861 - Service ARC | C100: 263145 - NONHLANHLA FAITH HLONGWANE | G100: 20140201 | J100: =IFERROR(VLOOKUP(C100,Lynette!$C$13:$D$1213,2,FALSE),0) | K100: =E100/D100-1
A101: N | B101: 67861 - Service ARC | C101: 263232 - KARABO TSEREMA | G101: 20140601 | H101: 20160407 | J101: =IFERROR(VLOOKUP(C101,Lynette!$C$13:$D$1213,2,FALSE),0) | K101: =E101/D101-1
A102: N | B102: 67861 - Service ARC | C102: 263627 - RIYAAZ MARGROSE | G102: 20151203 | J102: =IFERROR(VLOOKUP(C102,Lynette!$C$13:$D$1213,2,FALSE),0) | K102: =E102/D102-1
B103: 67861 - Service ARC | C103: 263694 - GLENDA JOAN VELDMAN | G103: 20160411 | J103: =IFERROR(VLOOKUP(C103,Lynette!$C$13:$D$1213,2,FALSE),0) | K103: =E103/D103-1
A104: N | B104: 67861 - Service ARC | C104: 263710 - REHUMILE PATRICIA JIYANE | G104: 20160601 | J104: =IFERROR(VLOOKUP(C104,Lynette!$C$13:$D$1213,2,FALSE),0) | K104: =E104/D104-1
A105: N | B105: 67861 - Service ARC | C105: 60900 - CAROL FINGLESON | G105: 20000601 | J105: =IFERROR(VLOOKUP(C105,Lynette!$C$13:$D$1213,2,FALSE),0) | K105: =E105/D105-1
A106: N | B106: 67861 - Service ARC | C106: 61820 - MAGARETHA GERALDINE LE ROUX | G106: 20110101 | J106: =IFERROR(VLOOKUP(C106,Lynette!$C$13:$D$1213,2,FALSE),0) | K106: =E106/D106-1
A107: N | B107: 67861 - Service ARC | C107: New 1 | J107: =IFERROR(VLOOKUP(C107,Lynette!$C$13:$D$1213,2,FALSE),0) | K107: =E107/D107-1
A108: N | B108: 67861 - Service ARC | C108: New 4 | J108: =IFERROR(VLOOKUP(C108,Lynette!$C$13:$D$1213,2,FALSE),0) | K108: =E108/D108-1
A109: N | B109: 67861 - Service ARC | C109: New 5 | J109: =IFERROR(VLOOKUP(C109,Lynette!$C$13:$D$1213,2,FALSE),0) | K109: =E109/D109-1
A110: N | B110: 67874 - RF Consulting | C110: 130117 - JOHANNES MAKGOBELA | G110: 20040601 | J110: =IFERROR(VLOOKUP(C110,Lynette!$C$13:$D$1213,2,FALSE),0) | K110: =E110/D110-1
...

Sheet Lynette
B1: AON PRD:PAYROLL
B2: ACTUAL | C2: CHECK
B3: 2016
B4: ANNUAL
B5: UNSPECIFIED DEPARTMENT
A9: BUSINESS UNIT | B9: DEPARTMENT | C9: EMPLOYEE CODE - NAME & SURNAME | D9: CLASSIFICATION
A11: BUSINESS UNIT | B11: DEPARTMENT | C11: EMPLOYEE CODE - NAME & SURNAME | D11: CLASSIFICATION
A12: EMPLOYEE BENEFITS
A13: EMPLOYEE BENEFITS | B13: 67862 - SERVICE SSC | C13: 11411 - SHAAHIDA ADAMS | D13: NET SALARY CHANGES
A14: EMPLOYEE BENEFITS | B14: 67852 - HEALTHCARE OPERATIONS | C14: 120102 - CLAUDIA LAHOUD | D14: NET SALARY CHANGES
A15: EMPLOYEE BENEFITS | B15: 67865 - HEALTHCARE TEAM3 | C15: 120110 - CELESTE AQUALINE LAWRENCE | D15: NET SALARY CHANGES
A16: EMPLOYEE BENEFITS | B16: 67874 - RF CONSULTING | C16: 130117 - JOHANNES MAKGOBELA | D16: NET SALARY CHANGES
A17: EMPLOYEE BENEFITS | B17: 67866 - HEALTHCARE TEAM4 | C17: 130142 - THULANI GIDEON MABENA | D17: '16
A18: EMPLOYEE BENEFITS | B18: 67855 - HEALTHCARE DURBAN | C18: 130307 - LUTHANDO MRWEBI | D18: SEPARATIONS - VOLUNTARY '16
A19: EMPLOYEE BENEFITS | B19: 67879 - QED PENSIONS | C19: 130314 - LILLIAN NEO MOAGI | D19: '16
A20: EMPLOYEE BENEFITS | B20: 67852 - HEALTHCARE OPERATIONS | C20: 140502 - JACQUELINE NEL | D20: NET SALARY CHANGES
A21: EMPLOYEE BENEFITS | B21: 67874 - RF CONSULTING | C21: 141106 - IGNATIUS NDLOVU | D21: NET SALARY CHANGES
A22: EMPLOYEE BENEFITS | B22: 67855 - HEALTHCARE DURBAN | C22: 141149 - NOSIPHO PORTIA NGXULELO | D22: '16
A23: EMPLOYEE BENEFITS | B23: 67865 - HEALTHCARE TEAM3 | C23: 151601 - BRENDA OPPERMAN | D23: NET SALARY CHANGES
A24: EMPLOYEE BENEFITS | B24: 67858 - HEALTH RISK MANAGEMENT | C24: 151608 - CHRISTINE CHARLOTTE OOSTHUIZEN | D24: NET SALARY CHANGES
... A161: EMPLOYEE BENEFITS | B161: 67885 - THE BENEFIT SOLUTION | C161: NEW 2 | D161: '16
A162: HEWITT EXIT
A163: HEWITT EXIT | B163: 67886 - RETIREMENT FUNDING FUTURE SALE | C163: 100129 - LEVERNE LAYLAHNE JAPPIE | D163: '16
A164: HEWITT EXIT | B164: 67887 - HEADOFFCE FUTURE SALE BUSINESS | C164: 1013 - VIRGINIA PODILE | D164: '16
A165: HEWITT EXIT | B165: 67886 - RETIREMENT FUNDING FUTURE SALE | C165: 11419 - JAMES JOSEPH ADAMS | D165: '16
A166: HEWITT EXIT | B166: 67886 - RETIREMENT FUNDING FUTURE SALE | C166: 130271 - BERESFORD LOUIS MARTIN | D166: '16
A167: HEWITT EXIT | B167: 67886 - RETIREMENT FUNDING FUTURE SALE | C167: 130292 - NKANYISO MPOFU | D167: '16
A168: HEWITT EXIT | B168: 67886 - RETIREMENT FUNDING FUTURE SALE | C168: 141101 - DIJON NKOMO | D168: '16
A169: HEWITT EXIT | B169: 67886 - RETIREMENT FUNDING FUTURE SALE | C169: 141123 - PETRONELLA ZANELE NKONYANE | D169: '16
A170: HEWITT EXIT | B170: 67886 - RETIREMENT FUNDING FUTURE SALE | C170: 180101 - GLENELG KABELO RAKALE | D170: '16
A171: HEWITT EXIT | B171: 67887 - HEADOFFCE FUTURE SALE BUSINESS | C171: 181547 - AIFHELI EDWARDS RAMBAU | D171: '16
A172: HEWITT EXIT | B172: 67886 - RETIREMENT FUNDING FUTURE SALE | C172: 181550 - NORMA GAIL RODRIGUES | D172: '16
A173: HEWITT EXIT | B173: 67886 - RETIREMENT FUNDING FUTURE SALE | C173: 181563 - REFILOE RELEBOHILE PALESA TINTE | D173: '16
A174: HEWITT EXIT | B174: 67886 - RETIREMENT FUNDING FUTURE SALE | C174: 190119 - MARCIA MARGARET JOHNSON | D174: '16
... A212: HEWITT EXIT | B212: 67886 - RETIREMENT FUNDING FUTURE SALE | C212: 151609 - BONITA OOSTHUIZEN | D212: '16
A213: RETAIL
A214: RETAIL | B214: 67754 - CORPORATE CAPE TOWN | C214: 100100 - GERDALENE JANSE VAN RENSBURG | D214: '16
A215: RETAIL | B215: 67787 - COMMERCIAL NEW CASTLE | C215: 100128 - MARIEET SUSANNA JACOBS | D215: NET SALARY CHANGES
A216: RETAIL | B216: 67780 - COMMERCIAL DURBAN | C216: 100132 - KESHINI JOSEPH | D216: NET SALARY CHANGES
A217: RETAIL | B217: 67785 - COMMERCIAL MAFIKENG | C217: 1016 - MAGGIE MIETA MATHIBE | D217: SEPARATIONS - INVOLUNTARY
A218: RETAIL | B218: 67782 - COMMERCIAL PORT ELIZABETH | C218: 1062 - GILLIAN ANN BARTON | D218: SEPARATIONS - INVOLUNTARY '16
A219: RETAIL | B219: 67930 - BRANCH OPERATIONS BLOEMFONTEIN | C219: 110701 - ADELINAH KGASANE | D219: RESTRUCTURING '16
A220: RETAIL | B220: 67784 - COMMERCIAL KIMBERLEY | C220: 110903 - ANNA ELIZABETH KITSHOFF | D220: RESTRUCTURING '16
A221: RETAIL | B221: 67781 - COMMERCIAL JOHANNESBURG | C221: 11405 - CHANINE COLETT SCHROEDER | D221: NET SALARY CHANGES
A222: RETAIL | B222: 67756 - CORPORATE JOHANNESBURG | C222: 11415 - ANITA SUSAN ADRIAANSE | D222: '16
A223: RETAIL | B223: 67754 - CORPORATE CAPE TOWN | C223: 1159 - NOMBULELO EDNA MKONDO | D223: '16
A224: RETAIL | B224: 67780 - COMMERCIAL DURBAN | C224: 11601 - NOAH JOSEPH APPALSAMY | D224: NET SALARY CHANGES
A225: RETAIL | B225: 67756 - CORPORATE JOHANNESBURG | C225: 120108 - JENNIFER LABUSCHAGNE | D225: NET SALARY CHANGES
... A1213: RETAIL | B1213: 67929 - HEAD OFFICE | C1213: 263187 - TERENCE WILLIAMS | D1213: NET SALARY CHANGES

Sheet KEY
G3: Break out = | J3: Also do a FTE (headcount)
C4: Add in mid term 2016 starters impact | G4: Restructure -
C5: Run rate impact | H5: Claims out | J5: new new | K5: per BU
H6: Retail out | J6: new replacement | K6: per BU
H7: Broking out | J7: transfers | K7: perhaps
H8: CFC out
H10: UNKNOWN LEAVER
H11: REPLACEMENTS
H12: SEPARATIONS - INVOLUNTARY
H13: NET SALARY CHANGES
H14: SEPARATIONS - VOLUNTARY
H15: NEW POSITIONS

Sheet Monthly2016
A1: CUBE: | B1: aon prd:Payroll
A2: aon prd:Year | B2: 2016
A3: aon prd:Version | B3: Working Forecast
C6: Jan | D6: Jan | E6: Feb | F6: Feb | G6: Mar | H6: Mar | I6: Apr | J6: Apr | K6: May | L6: May | M6: May | N6: Jun | O6: Jun | P6: Jul | Q6: Jul | R6: Jul | S6: Aug | T6: Aug | U6: Sep | V6: Sep | W6: Sep | X6: Oct | Y6: Oct | Z6: Oct | AA6: Nov | AB6: Nov | AC6: Dec | AD6: Dec | AE6: All Months | AF6: All Months | AG6: All Months
C7: Cash Component (D) | D7: Cash Component - Temp (D) | E7: Cash Component (D) | F7: Cash Component - Temp (D) | G7: Cash Component (D) | H7: Cash Component - Temp (D) | I7: Cash Component (D) | J7: Cash Component - Temp (D) | K7: Cash Component - Consultant (D) | L7: Cash Component (D) | M7: Cash Component - Temp (D) | N7: Cash Component (D) | O7: Cash Component - Temp (D) | P7: Cash Component - Consultant (D) | Q7: Cash Component (D) | R7: Cash Component - Temp (D) | S7: Cash Component (D) | T7: Cash Component - Temp (D) | U7: Cash Component - Consultant (D) | V7: Cash Component (D) | W7: Cash Component - Temp (D) | X7: Cash Component - Consultant (D) | Y7: Cash Component (D) | Z7: Cash Component - Temp (D) | AA7: Cash Component (D) | AB7: Cash Component - Temp (D) | AC7: Cash Component (D) | AD7: Cash Component - Temp (D) | AE7: Cash Component - Consultant (D) | AF7: Cash Component (D) | AG7: Cash Component - Temp (D) | AH7: Total
A8: 67891 - Hewitt McLagan | B8: 263313 - TYRONE BRUCE JANSEN | AH8: =SUM(AE8:AG8)
A9: 67852 - Healthcare Operations | B9: 120102 - CLAUDIA LAHOUD | AH9: =SUM(AE9:AG9)
A10: 67852 - Healthcare Operations | B10: 140502 - JACQUELINE NEL | AH10: =SUM(AE10:AG10)
A11: 67852 - Healthcare Operations | B11: 262434 - ANNAKE PEARCE | AH11: =SUM(AE11:AG11)
A12: 67852 - Healthcare Operations | B12: 262608 - GAVIN JOHN GRIFFIN | AH12: =SUM(AE12:AG12)
A13: 67852 - Healthcare Operations | B13: New 1 | AH13: =SUM(AE13:AG13)
A14: 67853 - Healthcare Bloemfontein | B14: 220537 - ANILIA BOSHOFF | AH14: =SUM(AE14:AG14)
A15: 67853 - Healthcare Bloemfontein | B15: 220554 - HELEN VAN HEERDEN | AH15: =SUM(AE15:AG15)
A16: 67853 - Healthcare Bloemfontein | B16: 263195 - LEONIE FOURIE | AH16: =SUM(AE16:AG16)
A17: 67854 - Healthcare Cape Town | B17: 220110 - MARGAUX VAN HUYSSTEEN | AH17: =SUM(AE17:AG17)
A18: 67854 - Healthcare Cape Town | B18: 260001 - VALENTINO YOUNG | AH18: =SUM(AE18:AG18)
A19: 67854 - Healthcare Cape Town | B19: 263398 - ANTON EUGENE FOSTER | AH19: =SUM(AE19:AG19)
... A101: GLOBAL BENEFITS (4200ZA) | B101: 262699 - THARANGANY SINGARAVELLOO | AH101: =SUM(AE101:AG101)

Sheet Monthly2017
C1: Annual | D1: Annual | E1: Annual | F1: Jan | G1: Jan | H1: Feb | I1: Feb | J1: Mar | K1: Mar | L1: Apr | M1: Apr | N1: May | O1: May | P1: Jun | Q1: Jun | R1: Jul | S1: Jul | T1: Aug | U1: Aug | V1: Sep | W1: Sep | X1: Oct | Y1: Oct | Z1: Nov | AA1: Nov | AB1: Dec | AC1: Dec | AD1: All Months | AE1: All Months
C2: Consultant TCTC | D2: Permanent TCTC | E2: Temp TCTC | F2: Permanent TCTC | G2: Temp TCTC | H2: Permanent TCTC | I2: Temp TCTC | J2: Permanent TCTC | K2: Temp TCTC | L2: Permanent TCTC | M2: Temp TCTC | N2: Permanent TCTC | O2: Temp TCTC | P2: Permanent TCTC | Q2: Temp TCTC | R2: Permanent TCTC | S2: Temp TCTC | T2: Permanent TCTC | U2: Temp TCTC | V2: Permanent TCTC | W2: Temp TCTC | X2: Permanent TCTC | Y2: Temp TCTC | Z2: Permanent TCTC | AA2: Temp TCTC | AB2: Permanent TCTC | AC2: Temp TCTC | AD2: Permanent TCTC | AE2: Temp TCTC | AF2: Total
A3: 67891 - Hewitt McLagan | B3: 263313 - TYRONE BRUCE JANSEN | AF3: =SUM(AD3:AE3)
A4: 67852 - Healthcare Operations | B4: 0 | AF4: =SUM(AD4:AE4)
A5: 67852 - Healthcare Operations | B5: 120102 - CLAUDIA LAHOUD | AF5: =SUM(AD5:AE5)
A6: 67852 - Healthcare Operations | B6: 140502 - JACQUELINE NEL | AF6: =SUM(AD6:AE6)
A7: 67852 - Healthcare Operations | B7: 262434 - ANNAKE PEARCE | AF7: =SUM(AD7:AE7)
A8: 67852 - Healthcare Operations | B8: 262608 - GAVIN JOHN GRIFFIN | AF8: =SUM(AD8:AE8)
A9: 67853 - Healthcare Bloemfontein | B9: 220537 - ANILIA BOSHOFF | AF9: =SUM(AD9:AE9)
A10: 67853 - Healthcare Bloemfontein | B10: 220554 - HELEN VAN HEERDEN | AF10: =SUM(AD10:AE10)
A11: 67853 - Healthcare Bloemfontein | B11: 263195 - LEONIE FOURIE | AF11: =SUM(AD11:AE11)
A12: 67854 - Healthcare Cape Town | B12: 220110 - MARGAUX VAN HUYSSTEEN | AF12: =SUM(AD12:AE12)
A13: 67854 - Healthcare Cape Town | B13: 260001 - VALENTINO YOUNG | AF13: =SUM(AD13:AE13)
A14: 67854 - Healthcare Cape Town | B14: 263398 - ANTON EUGENE FOSTER | AF14: =SUM(AD14:AE14)
... A86: GLOBAL BENEFITS (4200ZA) | B86: 262699 - THARANGANY SINGARAVELLOO | AF86: =SUM(AD86:AE86)

Sheet Sheet1
